pysun/__init__.py
pysun/pysun.py
Pysun-0.0.1.dist-info/LICENSE
Pysun-0.0.1.dist-info/METADATA
Pysun-0.0.1.dist-info/WHEEL
Pysun-0.0.1.dist-info/top_level.txt
Pysun-0.0.1.dist-info/RECORD
