Metadata-Version: 2.1
Name: Pysun
Version: 0.0.1
Summary: UNKNOWN
Home-page: UNKNOWN
Author: visual.ml
License: MIT
Keywords: window designer display
Platform: UNKNOWN
Requires-Dist: PySide2
